[
    {
        "id": "69f5be7d15ab0",
        "name": "test",
        "college": "birt",
        "email": "gautamsingh893591@gmail.com",
        "phone": "9661259888",
        "address": "e",
        "pincode": "efe2131",
        "slip": "https:\/\/raw.githubusercontent.com\/Gautamsingh45\/programming-contest\/master\/uploads\/1777712761_1.png",
        "status": "pending",
        "time": 1777712765
    },
    {
        "email": "gautamsingh893591@gmail.com",
        "name": "test",
        "slip": "https:\/\/raw.githubusercontent.com\/Gautamsingh45\/programming-contest\/master\/uploads\/1777713267_1.png",
        "status": "pending",
        "time": 1777713271
    },
    {
        "email": "gautamsingh893591@gmail.com",
        "name": "test",
        "slip": "https:\/\/raw.githubusercontent.com\/Gautamsingh45\/programming-contest\/master\/uploads\/1777713291_1.png",
        "status": "pending",
        "time": 1777713295
    },
    {
        "email": "gautamsingh893591@gmail.com",
        "name": "test",
        "slip": "https:\/\/raw.githubusercontent.com\/Gautamsingh45\/programming-contest\/master\/uploads\/1777713346_1.png",
        "status": "pending",
        "time": 1777713348
    },
    {
        "email": "gautamsingh893591@gmail.com",
        "name": "test",
        "slip": "https:\/\/raw.githubusercontent.com\/Gautamsingh45\/programming-contest\/master\/uploads\/1777713364_1.png",
        "status": "pending",
        "time": 1777713367
    },
    {
        "email": "gautamsingh893591@gmail.com",
        "name": "test",
        "slip": "https:\/\/raw.githubusercontent.com\/Gautamsingh45\/programming-contest\/master\/uploads\/1777713478_1.png",
        "status": "pending",
        "time": 1777713481
    },
    {
        "email": "gautamsingh893591@gmail.com",
        "name": "test",
        "slip": "https:\/\/raw.githubusercontent.com\/Gautamsingh45\/programming-contest\/master\/uploads\/1777713523_1.png",
        "status": "pending",
        "time": 1777713526
    },
    {
        "email": "gautamsingh893591@gmail.com",
        "name": "test",
        "slip": "https:\/\/raw.githubusercontent.com\/Gautamsingh45\/programming-contest\/master\/uploads\/1777714107_1.png",
        "status": "pending",
        "time": 1777714112
    },
    {
        "email": "gautamsinghtit2025@gmail.com",
        "name": "undefined",
        "slip": "https:\/\/raw.githubusercontent.com\/Gautamsingh45\/programming-contest\/master\/uploads\/1777714677_1.png",
        "status": "pending",
        "time": 1777714683
    },
    {
        "email": "gautamsingh893591@gmail.com",
        "name": "undefined",
        "slip": "https:\/\/raw.githubusercontent.com\/Gautamsingh45\/programming-contest\/master\/uploads\/1777714973_1.png",
        "status": "pending",
        "time": 1777714978
    },
    {
        "email": "gautamsingh893591@gmail.com",
        "name": "undefined",
        "slip": "https:\/\/raw.githubusercontent.com\/Gautamsingh45\/programming-contest\/master\/uploads\/1777715085_1.png",
        "status": "pending",
        "time": 1777715090
    },
    {
        "email": "gautamsingh893591@gmail.com",
        "name": "undefined",
        "slip": "https:\/\/raw.githubusercontent.com\/Gautamsingh45\/programming-contest\/master\/uploads\/1777715191_1.png",
        "status": "pending",
        "time": 1777715194
    }
]